notion_operator_py/__init__.py
notion_operator_py/builder.py
notion_operator_py/database.py
notion_operator_py/page.py
notion_operator_py/utils.py
notion_operator_py/objects/__init__.py
notion_operator_py/objects/common.py
notion_operator_py/objects/object.py
notion_operator_py/objects/properties.py
notion_operator_py-0.6.1.dist-info/LICENSE
notion_operator_py-0.6.1.dist-info/METADATA
notion_operator_py-0.6.1.dist-info/WHEEL
notion_operator_py-0.6.1.dist-info/top_level.txt
notion_operator_py-0.6.1.dist-info/RECORD
